pyrefinebio/__init__.py
pyrefinebio/annotation.py
pyrefinebio/api_interface.py
pyrefinebio/base.py
pyrefinebio/compendia.py
pyrefinebio/computational_result.py
pyrefinebio/computed_file.py
pyrefinebio/config.py
pyrefinebio/dataset.py
pyrefinebio/exceptions.py
pyrefinebio/experiment.py
pyrefinebio/high_level_functions.py
pyrefinebio/institution.py
pyrefinebio/job.py
pyrefinebio/organism.py
pyrefinebio/original_file.py
pyrefinebio/platform.py
pyrefinebio/processor.py
pyrefinebio/qn_target.py
pyrefinebio/sample.py
pyrefinebio/script.py
pyrefinebio/token.py
pyrefinebio/transcriptome_index.py
pyrefinebio/util.py
tests/__init__.py
tests/custom_assertions.py
tests/mocks.py
tests/test_api_interface.py
tests/test_compendia.py
tests/test_computational_result.py
tests/test_computed_file.py
tests/test_dataset.py
tests/test_downloader_job.py
tests/test_experiment.py
tests/test_high_level_functions.py
tests/test_institution.py
tests/test_organism.py
tests/test_original_file.py
tests/test_paginated_list.py
tests/test_platform.py
tests/test_processor.py
tests/test_processor_job.py
tests/test_qn_target.py
tests/test_sample.py
tests/test_script.py
tests/test_survey_job.py
tests/test_token.py
tests/test_transcriptome_index.py
pyrefinebio-0.4.10.dist-info/LICENSE
pyrefinebio-0.4.10.dist-info/METADATA
pyrefinebio-0.4.10.dist-info/WHEEL
pyrefinebio-0.4.10.dist-info/entry_points.txt
pyrefinebio-0.4.10.dist-info/top_level.txt
pyrefinebio-0.4.10.dist-info/RECORD
