Metadata-Version: 2.1
Name: pyrefinebio
Version: 0.4.10
Summary: A python client for the refine.bio API.
Home-page: https://github.com/AlexsLemonade/refinebio-py
Author: Childhood Cancer Data Lab
Author-email: ccdl@alexslemonade.org
Classifier: Programming Language :: Python :: 3
Classifier: License :: OSI Approved :: BSD License
Classifier: Operating System :: OS Independent
Requires-Python: >=3.6
License-File: LICENSE
Requires-Dist: iso8601
Requires-Dist: PyYAML
Requires-Dist: requests
Requires-Dist: Click
Requires-Dist: pytimeparse
